LICENSE
polybiblioglot/__init__.py
polybiblioglot/__main__.py
polybiblioglot/components/__init__.py
polybiblioglot/components/converter.py
polybiblioglot/components/translator.py
polybiblioglot/lang/__init__.py
polybiblioglot/lang/languages.py
polybiblioglot/polybiblioglot.py
polybiblioglot-0.2.0.dist-info/LICENSE
polybiblioglot-0.2.0.dist-info/WHEEL
polybiblioglot-0.2.0.dist-info/METADATA
polybiblioglot-0.2.0.dist-info/RECORD
