Metadata-Version: 2.1
Name: polybiblioglot
Version: 0.2.0
Summary: A tool to translate scanned books
Home-page: https://github.com/bruno-robert/polybiblioglot
Keywords: ocr,translation
Author: Bruno Robert
Author-email: bruno.jeanluke@icloud.com
Requires-Python: >=3.8,<4.0
Classifier: License :: OSI Approved :: GNU General Public License v3 (GPLv3)
Classifier: Programming Language :: Python :: 3
Classifier: Programming Language :: Python :: 3.8
Classifier: Programming Language :: Python :: 3.9
Requires-Dist: Pillow (>=8.1.2,<9.0.0)
Requires-Dist: dearpygui (==0.6.123)
Requires-Dist: pdf2image (>=1.14.0,<2.0.0)
Requires-Dist: pytesseract (>=0.3.7,<0.4.0)
Requires-Dist: requests (>=2.22.0,<3.0.0)
Requires-Dist: translate (>=3.5.0,<4.0.0)
Project-URL: Repository, https://github.com/bruno-robert/polybiblioglot
